betterplots/__about__.py
betterplots/__init__.py
betterplots/bettercorners/__init__.py
betterplots/bettercorners/main.py
betterplots/betterstyle/__init__.py
betterplots/betterstyle/betterstyle.mplstyle
betterplots/betterstyle/set_style.py
betterplots-0.1.dist-info/METADATA
betterplots-0.1.dist-info/WHEEL
betterplots-0.1.dist-info/licenses/LICENSE
betterplots-0.1.dist-info/RECORD
