Metadata-Version: 2.4
Name: betterplots
Version: 0.1
Summary: A matplotlib-style augmenter
Project-URL: Homepage, https://github.com/RhysAlfShaw/betterplots
Project-URL: Documentation, https://github.com/RhysAlfShaw/betterplots#readme
Project-URL: Issues, https://github.com/RhysAlfShaw/betterplots/issues
Project-URL: Source, https://github.com/RhysAlfShaw/betterplots
Author-email: Rhys Shaw <rhysc3p0@gmail.com>
License-Expression: GPL-3.0-or-later
License-File: LICENSE
Classifier: License :: OSI Approved :: GNU General Public License v3 or later (GPLv3+)
Classifier: Programming Language :: Python :: 3
Classifier: Programming Language :: Python :: 3.8
Classifier: Programming Language :: Python :: 3.9
Classifier: Programming Language :: Python :: 3.10
Classifier: Programming Language :: Python :: 3.11
Classifier: Programming Language :: Python :: 3.12
Requires-Python: >=3.8
Requires-Dist: matplotlib
